aioclashroyale/__init__.py
aioclashroyale/aioclashroyale.py
aioclashroyale/aioclashroyale.py~
aioclashroyale/client/__init__.py
aioclashroyale/client/aiohttp.py
aioclashroyale/client/route.py
aioclashroyale/client/route.py~
aioclashroyale/client/token.py
aioclashroyale/const/__init__.py
aioclashroyale/const/routes.py
aioclashroyale/const/routes.py~
aioclashroyale/exceptions/__init__.py
aioclashroyale/models/__init__.py
aioclashroyale/models/dto/__init__.py
aioclashroyale/models/dto/Arena.py
aioclashroyale/models/dto/Battle.py
aioclashroyale/models/dto/Challenge.py
aioclashroyale/models/dto/ChallengeChain.py
aioclashroyale/models/dto/ChallengeChain.py~
aioclashroyale/models/dto/ChallengeGameMode.py
aioclashroyale/models/dto/Chest.py
aioclashroyale/models/dto/Clan.py
aioclashroyale/models/dto/ClanMember.py
aioclashroyale/models/dto/ClanRanking.py
aioclashroyale/models/dto/ClanWarClan.py
aioclashroyale/models/dto/ClanWarClan.py~
aioclashroyale/models/dto/ClanWarLog.py
aioclashroyale/models/dto/ClanWarParticipant.py
aioclashroyale/models/dto/ClanWarParticipant.py~
aioclashroyale/models/dto/ClanWarStanding.py
aioclashroyale/models/dto/ClanWarStanding.py~
aioclashroyale/models/dto/CurrentRiverRace.py
aioclashroyale/models/dto/Cursors.py
aioclashroyale/models/dto/File.py
aioclashroyale/models/dto/FingerPrint.py
aioclashroyale/models/dto/GameMode.py
aioclashroyale/models/dto/IconUrls.py
aioclashroyale/models/dto/Item.py
aioclashroyale/models/dto/Item.py~
aioclashroyale/models/dto/Items.py
aioclashroyale/models/dto/LadderTournament.py
aioclashroyale/models/dto/LadderTournamentRanking.py
aioclashroyale/models/dto/Leaderboard.py
aioclashroyale/models/dto/LeagueSeason.py
aioclashroyale/models/dto/LeagueSeason.py~
aioclashroyale/models/dto/LeagueSeasonResult.py
aioclashroyale/models/dto/LeagueSeasonV2.py
aioclashroyale/models/dto/Location.py
aioclashroyale/models/dto/PaginatedList.py
aioclashroyale/models/dto/Paging.py
aioclashroyale/models/dto/PathOfLegendSeasonResult.py
aioclashroyale-0.1.0.dist-info/LICENSE
aioclashroyale-0.1.0.dist-info/METADATA
aioclashroyale-0.1.0.dist-info/WHEEL
aioclashroyale-0.1.0.dist-info/RECORD
