Metadata-Version: 2.3
Name: aioclashroyale
Version: 0.1.0
Summary: Clash Royale API Wrapper
License: Apache License
Keywords: clashroyale,clash royale wrapper
Author: TallSmaN
Author-email: coffi435@gmail.com
Requires-Python: >=3.12
Classifier: Development Status :: 4 - Beta
Classifier: Intended Audience :: Developers
Classifier: Topic :: Software Development :: Libraries :: Python Modules
Classifier: Programming Language :: Python :: 3
Classifier: Programming Language :: Python :: 3.12
Classifier: License :: OSI Approved :: Apache Software License
Classifier: Operating System :: OS Independent
Requires-Dist: aiohttp (>=3.11.11,<4.0.0)
Requires-Dist: envparse (>=0.2.0,<0.3.0)
Requires-Dist: msgspec (>=0.19.0,<0.20.0)
Requires-Dist: pretty-errors (>=1.2.25,<2.0.0)
Project-URL: Repository, https://github.com/TallSmaN/aioclashroyale
